setup.py
src/big_o/__init__.py
src/big_o/big_o.py
src/big_o/complexities.py
src/big_o/datagen.py
big_o_pbeekes-0.0.1.dist-info/METADATA
big_o_pbeekes-0.0.1.dist-info/WHEEL
big_o_pbeekes-0.0.1.dist-info/licenses/LICENSE.txt
big_o_pbeekes-0.0.1.dist-info/RECORD
