Metadata-Version: 2.1
Name: big_o_pbeekes
Version: 0.0.1
Summary: big_O is a Python module to estimate the time complexity of Python code from its execution time. It can be used to analyze how functions scale with inputs of increasing size.
Project-URL: Homepage, https://github.com/pypa/sampleproject
Project-URL: Bug Tracker, https://github.com/pypa/sampleproject/issues
Author-email: Pbeekes <Pbeekes@example.com>, JPphilips <Jpphilips@example.com>
License-File: LICENSE.txt
Classifier: License :: OSI Approved :: MIT License
Classifier: Operating System :: OS Independent
Classifier: Programming Language :: Python :: 3
Requires-Python: >=3.7
